{
  "id": "system_fault_detected",
  "title": {
    "en": "System fault detected",
    "nl": "Systeemfout gedetecteerd"
  },
  "titleFormatted": {
    "en": "System fault detected",
    "nl": "Systeemfout gedetecteerd"
  },
  "hint": {
    "en": "Triggered when system faults are detected",
    "nl": "Geactiveerd wanneer systeemfouten worden gedetecteerd"
  },
  "tokens": [
    {
      "name": "message",
      "type": "string",
      "title": {
        "en": "System Fault Details",
        "nl": "Systeemfout Details"
      }
    }
  ],
  "args": [],
  "filter": "driver_id=venus"
}